README.md
setup.py
redis_enterpriseadmin.egg-info/PKG-INFO
redis_enterpriseadmin.egg-info/SOURCES.txt
redis_enterpriseadmin.egg-info/dependency_links.txt
redis_enterpriseadmin.egg-info/requires.txt
redis_enterpriseadmin.egg-info/top_level.txt
swagger_client/__init__.py
swagger_client/api_client.py
swagger_client/configuration.py
swagger_client/rest.py
swagger_client/api/__init__.py
swagger_client/api/default_api.py
swagger_client/models/__init__.py
test/__init__.py
test/test_default_api.py