Metadata-Version: 2.1
Name: redis-enterpriseadmin
Version: 0.0.1
Summary: An API wrapper for the redis enterprise EST api.
Home-page: UNKNOWN
Author-email: RedisLabs OSS <oss@redis.io>
License: UNKNOWN
Keywords: redis,rest,redis-enterprise
Platform: UNKNOWN
Classifier: Development Status :: 3 - Alpha
Classifier: Environment :: Console
Classifier: Intended Audience :: Developers
Classifier: Operating System :: OS Independent
Classifier: Programming Language :: Python
Classifier: Programming Language :: Python :: 3
Classifier: Programming Language :: Python :: 3 :: Only
Classifier: Programming Language :: Python :: 3.7
Classifier: Programming Language :: Python :: 3.8
Classifier: Programming Language :: Python :: 3.9
Classifier: Programming Language :: Python :: 3.10
Classifier: Programming Language :: Python :: 3.11
Classifier: Programming Language :: Python :: Implementation :: CPython
Classifier: Programming Language :: Python :: Implementation :: PyPy
